{"dependencies":[{"name":"/Users/pch33/develop/carousel-ui/package.json","includedInParent":true,"mtime":1522893784000},{"name":"./style.css","loc":{"line":1,"column":7}},{"name":"../getFixedIndex","loc":{"line":2,"column":26}}],"generated":{"js":"'use strict';\n\nObject.defineProperty(exports, \"__esModule\", {\n  value: true\n});\n\nrequire('./style.css');\n\nvar _getFixedIndex = require('../getFixedIndex');\n\nvar _getFixedIndex2 = _interopRequireDefault(_getFixedIndex);\n\nfunction _interopRequireDefault(obj) { return obj && obj.__esModule ? obj : { default: obj }; }\n\nvar create = function create(_ref) {\n  var width = _ref.width,\n      height = _ref.height,\n      num = _ref.num,\n      srcList = _ref.srcList,\n      _ref$startIndex = _ref.startIndex,\n      startIndex = _ref$startIndex === undefined ? 0 : _ref$startIndex;\n\n  var resetWidth = function resetWidth() {\n    container.style.width = width * num;\n  };\n\n  var getImage = function getImage(index) {\n    var fixedIndex = (0, _getFixedIndex2.default)(srcList, index);\n\n    var src = srcList[fixedIndex];\n    var image = new Image(width, height);\n    image.src = src;\n\n    return image;\n  };\n\n  var next = function next() {\n    current += 1;\n\n    var newImage = getImage(current + (num - 1));\n    container.insertAdjacentElement('beforeend', newImage);\n\n    var firstImage = container.querySelector('img:first-child');\n    firstImage.remove();\n  };\n\n  var pre = function pre() {\n    current -= 1;\n\n    var newImage = getImage(current);\n    container.insertAdjacentElement('afterbegin', newImage);\n\n    var lastImage = container.querySelector('img:last-child');\n    lastImage.remove();\n  };\n\n  var container = document.createElement('div');\n  container.className = 'images-container';\n  resetWidth();\n\n  var current = startIndex;\n  for (var i = 0; i < num; i += 1) {\n    var image = getImage(current + i);\n    container.insertAdjacentElement('beforeend', image);\n  }\n  // current += num\n\n  return {\n    next: next,\n    pre: pre,\n    addSrc: function addSrc(src) {\n      srcList.psuh(src);\n      resetWidth();\n    },\n    removeSrc: function removeSrc(targetSrc) {\n      srcList = srcList.filter(function (src) {\n        return src === targetSrc;\n      });\n      resetWidth();\n    },\n    getContainer: function getContainer() {\n      return container;\n    }\n  };\n};\n\nexports.default = {\n  create: create\n};","map":{"mappings":[{"generated":{"line":7,"column":0},"source":"src/lib/Images/index.js","original":{"line":1,"column":0}},{"generated":{"line":9,"column":0},"source":"src/lib/Images/index.js","original":{"line":2,"column":0}},{"generated":{"line":15,"column":0},"source":"src/lib/Images/index.js","original":{"line":4,"column":0}},{"name":"create","generated":{"line":15,"column":4},"source":"src/lib/Images/index.js","original":{"line":4,"column":6}},{"generated":{"line":15,"column":13},"source":"src/lib/Images/index.js","original":{"line":4,"column":15}},{"name":"create","generated":{"line":15,"column":22},"source":"src/lib/Images/index.js","original":{"line":4,"column":6}},{"generated":{"line":15,"column":28},"source":"src/lib/Images/index.js","original":{"line":4,"column":15}},{"generated":{"line":15,"column":35},"source":"src/lib/Images/index.js","original":{"line":6,"column":6}},{"generated":{"line":16,"column":0},"source":"src/lib/Images/index.js","original":{"line":6,"column":6}},{"name":"width","generated":{"line":16,"column":6},"source":"src/lib/Images/index.js","original":{"line":5,"column":2}},{"generated":{"line":16,"column":11},"source":"src/lib/Images/index.js","original":{"line":6,"column":6}},{"name":"width","generated":{"line":16,"column":19},"source":"src/lib/Images/index.js","original":{"line":5,"column":2}},{"generated":{"line":16,"column":24},"source":"src/lib/Images/index.js","original":{"line":6,"column":6}},{"generated":{"line":17,"column":0},"source":"src/lib/Images/index.js","original":{"line":6,"column":6}},{"name":"height","generated":{"line":17,"column":6},"source":"src/lib/Images/index.js","original":{"line":5,"column":9}},{"generated":{"line":17,"column":12},"source":"src/lib/Images/index.js","original":{"line":6,"column":6}},{"name":"height","generated":{"line":17,"column":20},"source":"src/lib/Images/index.js","original":{"line":5,"column":9}},{"generated":{"line":17,"column":26},"source":"src/lib/Images/index.js","original":{"line":6,"column":6}},{"generated":{"line":18,"column":0},"source":"src/lib/Images/index.js","original":{"line":6,"column":6}},{"name":"num","generated":{"line":18,"column":6},"source":"src/lib/Images/index.js","original":{"line":5,"column":17}},{"generated":{"line":18,"column":9},"source":"src/lib/Images/index.js","original":{"line":6,"column":6}},{"name":"num","generated":{"line":18,"column":17},"source":"src/lib/Images/index.js","original":{"line":5,"column":17}},{"generated":{"line":18,"column":20},"source":"src/lib/Images/index.js","original":{"line":6,"column":6}},{"generated":{"line":19,"column":0},"source":"src/lib/Images/index.js","original":{"line":6,"column":6}},{"name":"srcList","generated":{"line":19,"column":6},"source":"src/lib/Images/index.js","original":{"line":5,"column":22}},{"generated":{"line":19,"column":13},"source":"src/lib/Images/index.js","original":{"line":6,"column":6}},{"name":"srcList","generated":{"line":19,"column":21},"source":"src/lib/Images/index.js","original":{"line":5,"column":22}},{"generated":{"line":19,"column":28},"source":"src/lib/Images/index.js","original":{"line":6,"column":6}},{"generated":{"line":20,"column":0},"source":"src/lib/Images/index.js","original":{"line":6,"column":6}},{"name":"startIndex","generated":{"line":20,"column":29},"source":"src/lib/Images/index.js","original":{"line":5,"column":31}},{"generated":{"line":20,"column":39},"source":"src/lib/Images/index.js","original":{"line":6,"column":6}},{"generated":{"line":21,"column":0},"source":"src/lib/Images/index.js","original":{"line":6,"column":6}},{"name":"startIndex","generated":{"line":21,"column":6},"source":"src/lib/Images/index.js","original":{"line":5,"column":31}},{"generated":{"line":21,"column":16},"source":"src/lib/Images/index.js","original":{"line":6,"column":6}},{"generated":{"line":21,"column":51},"source":"src/lib/Images/index.js","original":{"line":5,"column":44}},{"generated":{"line":21,"column":52},"source":"src/lib/Images/index.js","original":{"line":6,"column":6}},{"generated":{"line":23,"column":0},"source":"src/lib/Images/index.js","original":{"line":7,"column":2}},{"name":"resetWidth","generated":{"line":23,"column":6},"source":"src/lib/Images/index.js","original":{"line":7,"column":8}},{"generated":{"line":23,"column":19},"source":"src/lib/Images/index.js","original":{"line":7,"column":21}},{"name":"resetWidth","generated":{"line":23,"column":28},"source":"src/lib/Images/index.js","original":{"line":7,"column":8}},{"generated":{"line":23,"column":38},"source":"src/lib/Images/index.js","original":{"line":7,"column":21}},{"generated":{"line":23,"column":41},"source":"src/lib/Images/index.js","original":{"line":7,"column":27}},{"name":"container","generated":{"line":24,"column":0},"source":"src/lib/Images/index.js","original":{"line":8,"column":4}},{"name":"style","generated":{"line":24,"column":14},"source":"src/lib/Images/index.js","original":{"line":8,"column":14}},{"generated":{"line":24,"column":19},"source":"src/lib/Images/index.js","original":{"line":8,"column":4}},{"name":"width","generated":{"line":24,"column":20},"source":"src/lib/Images/index.js","original":{"line":8,"column":20}},{"generated":{"line":24,"column":25},"source":"src/lib/Images/index.js","original":{"line":8,"column":4}},{"name":"width","generated":{"line":24,"column":28},"source":"src/lib/Images/index.js","original":{"line":8,"column":28}},{"name":"num","generated":{"line":24,"column":36},"source":"src/lib/Images/index.js","original":{"line":8,"column":36}},{"generated":{"line":24,"column":39},"source":"src/lib/Images/index.js","original":{"line":8,"column":4}},{"generated":{"line":25,"column":0},"source":"src/lib/Images/index.js","original":{"line":9,"column":3}},{"generated":{"line":25,"column":3},"source":"src/lib/Images/index.js","original":{"line":7,"column":2}},{"generated":{"line":27,"column":0},"source":"src/lib/Images/index.js","original":{"line":11,"column":2}},{"name":"getImage","generated":{"line":27,"column":6},"source":"src/lib/Images/index.js","original":{"line":11,"column":8}},{"generated":{"line":27,"column":17},"source":"src/lib/Images/index.js","original":{"line":11,"column":19}},{"name":"getImage","generated":{"line":27,"column":26},"source":"src/lib/Images/index.js","original":{"line":11,"column":8}},{"generated":{"line":27,"column":34},"source":"src/lib/Images/index.js","original":{"line":11,"column":19}},{"name":"index","generated":{"line":27,"column":35},"source":"src/lib/Images/index.js","original":{"line":11,"column":20}},{"generated":{"line":27,"column":40},"source":"src/lib/Images/index.js","original":{"line":11,"column":19}},{"generated":{"line":27,"column":42},"source":"src/lib/Images/index.js","original":{"line":11,"column":30}},{"generated":{"line":28,"column":0},"source":"src/lib/Images/index.js","original":{"line":12,"column":4}},{"name":"fixedIndex","generated":{"line":28,"column":8},"source":"src/lib/Images/index.js","original":{"line":12,"column":10}},{"generated":{"line":28,"column":21},"source":"src/lib/Images/index.js","original":{"line":12,"column":23}},{"name":"srcList","generated":{"line":28,"column":50},"source":"src/lib/Images/index.js","original":{"line":12,"column":37}},{"generated":{"line":28,"column":57},"source":"src/lib/Images/index.js","original":{"line":12,"column":23}},{"name":"index","generated":{"line":28,"column":59},"source":"src/lib/Images/index.js","original":{"line":12,"column":46}},{"generated":{"line":28,"column":64},"source":"src/lib/Images/index.js","original":{"line":12,"column":23}},{"generated":{"line":28,"column":65},"source":"src/lib/Images/index.js","original":{"line":12,"column":4}},{"generated":{"line":30,"column":0},"source":"src/lib/Images/index.js","original":{"line":14,"column":4}},{"name":"src","generated":{"line":30,"column":8},"source":"src/lib/Images/index.js","original":{"line":14,"column":10}},{"name":"srcList","generated":{"line":30,"column":14},"source":"src/lib/Images/index.js","original":{"line":14,"column":16}},{"name":"fixedIndex","generated":{"line":30,"column":22},"source":"src/lib/Images/index.js","original":{"line":14,"column":24}},{"generated":{"line":30,"column":32},"source":"src/lib/Images/index.js","original":{"line":14,"column":16}},{"generated":{"line":30,"column":33},"source":"src/lib/Images/index.js","original":{"line":14,"column":4}},{"generated":{"line":31,"column":0},"source":"src/lib/Images/index.js","original":{"line":15,"column":4}},{"name":"image","generated":{"line":31,"column":8},"source":"src/lib/Images/index.js","original":{"line":15,"column":10}},{"generated":{"line":31,"column":16},"source":"src/lib/Images/index.js","original":{"line":15,"column":18}},{"name":"Image","generated":{"line":31,"column":20},"source":"src/lib/Images/index.js","original":{"line":15,"column":22}},{"generated":{"line":31,"column":25},"source":"src/lib/Images/index.js","original":{"line":15,"column":18}},{"name":"width","generated":{"line":31,"column":26},"source":"src/lib/Images/index.js","original":{"line":15,"column":28}},{"generated":{"line":31,"column":31},"source":"src/lib/Images/index.js","original":{"line":15,"column":18}},{"name":"height","generated":{"line":31,"column":33},"source":"src/lib/Images/index.js","original":{"line":15,"column":35}},{"generated":{"line":31,"column":39},"source":"src/lib/Images/index.js","original":{"line":15,"column":18}},{"generated":{"line":31,"column":40},"source":"src/lib/Images/index.js","original":{"line":15,"column":4}},{"name":"image","generated":{"line":32,"column":0},"source":"src/lib/Images/index.js","original":{"line":16,"column":4}},{"name":"src","generated":{"line":32,"column":10},"source":"src/lib/Images/index.js","original":{"line":16,"column":10}},{"generated":{"line":32,"column":13},"source":"src/lib/Images/index.js","original":{"line":16,"column":4}},{"name":"src","generated":{"line":32,"column":16},"source":"src/lib/Images/index.js","original":{"line":16,"column":16}},{"generated":{"line":32,"column":19},"source":"src/lib/Images/index.js","original":{"line":16,"column":4}},{"generated":{"line":34,"column":0},"source":"src/lib/Images/index.js","original":{"line":18,"column":4}},{"name":"image","generated":{"line":34,"column":11},"source":"src/lib/Images/index.js","original":{"line":18,"column":11}},{"generated":{"line":34,"column":16},"source":"src/lib/Images/index.js","original":{"line":18,"column":4}},{"generated":{"line":35,"column":0},"source":"src/lib/Images/index.js","original":{"line":19,"column":3}},{"generated":{"line":35,"column":3},"source":"src/lib/Images/index.js","original":{"line":11,"column":2}},{"generated":{"line":37,"column":0},"source":"src/lib/Images/index.js","original":{"line":21,"column":2}},{"name":"next","generated":{"line":37,"column":6},"source":"src/lib/Images/index.js","original":{"line":21,"column":8}},{"generated":{"line":37,"column":13},"source":"src/lib/Images/index.js","original":{"line":21,"column":15}},{"name":"next","generated":{"line":37,"column":22},"source":"src/lib/Images/index.js","original":{"line":21,"column":8}},{"generated":{"line":37,"column":26},"source":"src/lib/Images/index.js","original":{"line":21,"column":15}},{"generated":{"line":37,"column":29},"source":"src/lib/Images/index.js","original":{"line":21,"column":21}},{"name":"current","generated":{"line":38,"column":0},"source":"src/lib/Images/index.js","original":{"line":22,"column":4}},{"generated":{"line":38,"column":15},"source":"src/lib/Images/index.js","original":{"line":22,"column":15}},{"generated":{"line":38,"column":16},"source":"src/lib/Images/index.js","original":{"line":22,"column":4}},{"generated":{"line":40,"column":0},"source":"src/lib/Images/index.js","original":{"line":24,"column":4}},{"name":"newImage","generated":{"line":40,"column":8},"source":"src/lib/Images/index.js","original":{"line":24,"column":10}},{"name":"getImage","generated":{"line":40,"column":19},"source":"src/lib/Images/index.js","original":{"line":24,"column":21}},{"name":"current","generated":{"line":40,"column":28},"source":"src/lib/Images/index.js","original":{"line":24,"column":30}},{"name":"num","generated":{"line":40,"column":39},"source":"src/lib/Images/index.js","original":{"line":24,"column":41}},{"generated":{"line":40,"column":45},"source":"src/lib/Images/index.js","original":{"line":24,"column":47}},{"generated":{"line":40,"column":46},"source":"src/lib/Images/index.js","original":{"line":24,"column":30}},{"generated":{"line":40,"column":47},"source":"src/lib/Images/index.js","original":{"line":24,"column":21}},{"generated":{"line":40,"column":48},"source":"src/lib/Images/index.js","original":{"line":24,"column":4}},{"name":"container","generated":{"line":41,"column":0},"source":"src/lib/Images/index.js","original":{"line":25,"column":4}},{"name":"insertAdjacentElement","generated":{"line":41,"column":14},"source":"src/lib/Images/index.js","original":{"line":25,"column":14}},{"generated":{"line":41,"column":35},"source":"src/lib/Images/index.js","original":{"line":25,"column":4}},{"generated":{"line":41,"column":36},"source":"src/lib/Images/index.js","original":{"line":25,"column":36}},{"generated":{"line":41,"column":47},"source":"src/lib/Images/index.js","original":{"line":25,"column":4}},{"name":"newImage","generated":{"line":41,"column":49},"source":"src/lib/Images/index.js","original":{"line":25,"column":49}},{"generated":{"line":41,"column":57},"source":"src/lib/Images/index.js","original":{"line":25,"column":4}},{"generated":{"line":43,"column":0},"source":"src/lib/Images/index.js","original":{"line":27,"column":4}},{"name":"firstImage","generated":{"line":43,"column":8},"source":"src/lib/Images/index.js","original":{"line":27,"column":10}},{"name":"container","generated":{"line":43,"column":21},"source":"src/lib/Images/index.js","original":{"line":27,"column":23}},{"name":"querySelector","generated":{"line":43,"column":31},"source":"src/lib/Images/index.js","original":{"line":27,"column":33}},{"generated":{"line":43,"column":44},"source":"src/lib/Images/index.js","original":{"line":27,"column":23}},{"generated":{"line":43,"column":45},"source":"src/lib/Images/index.js","original":{"line":27,"column":47}},{"generated":{"line":43,"column":62},"source":"src/lib/Images/index.js","original":{"line":27,"column":23}},{"generated":{"line":43,"column":63},"source":"src/lib/Images/index.js","original":{"line":27,"column":4}},{"name":"firstImage","generated":{"line":44,"column":0},"source":"src/lib/Images/index.js","original":{"line":28,"column":4}},{"name":"remove","generated":{"line":44,"column":15},"source":"src/lib/Images/index.js","original":{"line":28,"column":15}},{"generated":{"line":44,"column":21},"source":"src/lib/Images/index.js","original":{"line":28,"column":4}},{"generated":{"line":45,"column":0},"source":"src/lib/Images/index.js","original":{"line":29,"column":3}},{"generated":{"line":45,"column":3},"source":"src/lib/Images/index.js","original":{"line":21,"column":2}},{"generated":{"line":47,"column":0},"source":"src/lib/Images/index.js","original":{"line":31,"column":2}},{"name":"pre","generated":{"line":47,"column":6},"source":"src/lib/Images/index.js","original":{"line":31,"column":8}},{"generated":{"line":47,"column":12},"source":"src/lib/Images/index.js","original":{"line":31,"column":14}},{"name":"pre","generated":{"line":47,"column":21},"source":"src/lib/Images/index.js","original":{"line":31,"column":8}},{"generated":{"line":47,"column":24},"source":"src/lib/Images/index.js","original":{"line":31,"column":14}},{"generated":{"line":47,"column":27},"source":"src/lib/Images/index.js","original":{"line":31,"column":20}},{"name":"current","generated":{"line":48,"column":0},"source":"src/lib/Images/index.js","original":{"line":32,"column":4}},{"generated":{"line":48,"column":15},"source":"src/lib/Images/index.js","original":{"line":32,"column":15}},{"generated":{"line":48,"column":16},"source":"src/lib/Images/index.js","original":{"line":32,"column":4}},{"generated":{"line":50,"column":0},"source":"src/lib/Images/index.js","original":{"line":34,"column":4}},{"name":"newImage","generated":{"line":50,"column":8},"source":"src/lib/Images/index.js","original":{"line":34,"column":10}},{"name":"getImage","generated":{"line":50,"column":19},"source":"src/lib/Images/index.js","original":{"line":34,"column":21}},{"name":"current","generated":{"line":50,"column":28},"source":"src/lib/Images/index.js","original":{"line":34,"column":30}},{"generated":{"line":50,"column":35},"source":"src/lib/Images/index.js","original":{"line":34,"column":21}},{"generated":{"line":50,"column":36},"source":"src/lib/Images/index.js","original":{"line":34,"column":4}},{"name":"container","generated":{"line":51,"column":0},"source":"src/lib/Images/index.js","original":{"line":35,"column":4}},{"name":"insertAdjacentElement","generated":{"line":51,"column":14},"source":"src/lib/Images/index.js","original":{"line":35,"column":14}},{"generated":{"line":51,"column":35},"source":"src/lib/Images/index.js","original":{"line":35,"column":4}},{"generated":{"line":51,"column":36},"source":"src/lib/Images/index.js","original":{"line":35,"column":36}},{"generated":{"line":51,"column":48},"source":"src/lib/Images/index.js","original":{"line":35,"column":4}},{"name":"newImage","generated":{"line":51,"column":50},"source":"src/lib/Images/index.js","original":{"line":35,"column":50}},{"generated":{"line":51,"column":58},"source":"src/lib/Images/index.js","original":{"line":35,"column":4}},{"generated":{"line":53,"column":0},"source":"src/lib/Images/index.js","original":{"line":37,"column":4}},{"name":"lastImage","generated":{"line":53,"column":8},"source":"src/lib/Images/index.js","original":{"line":37,"column":10}},{"name":"container","generated":{"line":53,"column":20},"source":"src/lib/Images/index.js","original":{"line":37,"column":22}},{"name":"querySelector","generated":{"line":53,"column":30},"source":"src/lib/Images/index.js","original":{"line":37,"column":32}},{"generated":{"line":53,"column":43},"source":"src/lib/Images/index.js","original":{"line":37,"column":22}},{"generated":{"line":53,"column":44},"source":"src/lib/Images/index.js","original":{"line":37,"column":46}},{"generated":{"line":53,"column":60},"source":"src/lib/Images/index.js","original":{"line":37,"column":22}},{"generated":{"line":53,"column":61},"source":"src/lib/Images/index.js","original":{"line":37,"column":4}},{"name":"lastImage","generated":{"line":54,"column":0},"source":"src/lib/Images/index.js","original":{"line":38,"column":4}},{"name":"remove","generated":{"line":54,"column":14},"source":"src/lib/Images/index.js","original":{"line":38,"column":14}},{"generated":{"line":54,"column":20},"source":"src/lib/Images/index.js","original":{"line":38,"column":4}},{"generated":{"line":55,"column":0},"source":"src/lib/Images/index.js","original":{"line":39,"column":3}},{"generated":{"line":55,"column":3},"source":"src/lib/Images/index.js","original":{"line":31,"column":2}},{"generated":{"line":57,"column":0},"source":"src/lib/Images/index.js","original":{"line":41,"column":2}},{"name":"container","generated":{"line":57,"column":6},"source":"src/lib/Images/index.js","original":{"line":41,"column":8}},{"name":"document","generated":{"line":57,"column":18},"source":"src/lib/Images/index.js","original":{"line":41,"column":20}},{"name":"createElement","generated":{"line":57,"column":27},"source":"src/lib/Images/index.js","original":{"line":41,"column":29}},{"generated":{"line":57,"column":40},"source":"src/lib/Images/index.js","original":{"line":41,"column":20}},{"generated":{"line":57,"column":41},"source":"src/lib/Images/index.js","original":{"line":41,"column":43}},{"generated":{"line":57,"column":46},"source":"src/lib/Images/index.js","original":{"line":41,"column":20}},{"generated":{"line":57,"column":47},"source":"src/lib/Images/index.js","original":{"line":41,"column":2}},{"name":"container","generated":{"line":58,"column":0},"source":"src/lib/Images/index.js","original":{"line":42,"column":2}},{"name":"className","generated":{"line":58,"column":12},"source":"src/lib/Images/index.js","original":{"line":42,"column":12}},{"generated":{"line":58,"column":21},"source":"src/lib/Images/index.js","original":{"line":42,"column":2}},{"generated":{"line":58,"column":24},"source":"src/lib/Images/index.js","original":{"line":42,"column":24}},{"generated":{"line":58,"column":42},"source":"src/lib/Images/index.js","original":{"line":42,"column":2}},{"name":"resetWidth","generated":{"line":59,"column":0},"source":"src/lib/Images/index.js","original":{"line":43,"column":2}},{"generated":{"line":61,"column":0},"source":"src/lib/Images/index.js","original":{"line":45,"column":2}},{"name":"current","generated":{"line":61,"column":6},"source":"src/lib/Images/index.js","original":{"line":45,"column":6}},{"name":"startIndex","generated":{"line":61,"column":16},"source":"src/lib/Images/index.js","original":{"line":45,"column":16}},{"generated":{"line":61,"column":26},"source":"src/lib/Images/index.js","original":{"line":45,"column":2}},{"generated":{"line":62,"column":0},"source":"src/lib/Images/index.js","original":{"line":46,"column":2}},{"generated":{"line":62,"column":7},"source":"src/lib/Images/index.js","original":{"line":46,"column":7}},{"name":"i","generated":{"line":62,"column":11},"source":"src/lib/Images/index.js","original":{"line":46,"column":11}},{"generated":{"line":62,"column":15},"source":"src/lib/Images/index.js","original":{"line":46,"column":15}},{"generated":{"line":62,"column":16},"source":"src/lib/Images/index.js","original":{"line":46,"column":2}},{"name":"i","generated":{"line":62,"column":18},"source":"src/lib/Images/index.js","original":{"line":46,"column":18}},{"name":"num","generated":{"line":62,"column":22},"source":"src/lib/Images/index.js","original":{"line":46,"column":22}},{"generated":{"line":62,"column":25},"source":"src/lib/Images/index.js","original":{"line":46,"column":2}},{"name":"i","generated":{"line":62,"column":27},"source":"src/lib/Images/index.js","original":{"line":46,"column":27}},{"generated":{"line":62,"column":32},"source":"src/lib/Images/index.js","original":{"line":46,"column":32}},{"generated":{"line":62,"column":33},"source":"src/lib/Images/index.js","original":{"line":46,"column":2}},{"generated":{"line":62,"column":35},"source":"src/lib/Images/index.js","original":{"line":46,"column":35}},{"generated":{"line":63,"column":0},"source":"src/lib/Images/index.js","original":{"line":47,"column":4}},{"name":"image","generated":{"line":63,"column":8},"source":"src/lib/Images/index.js","original":{"line":47,"column":10}},{"name":"getImage","generated":{"line":63,"column":16},"source":"src/lib/Images/index.js","original":{"line":47,"column":18}},{"name":"current","generated":{"line":63,"column":25},"source":"src/lib/Images/index.js","original":{"line":47,"column":27}},{"name":"i","generated":{"line":63,"column":35},"source":"src/lib/Images/index.js","original":{"line":47,"column":37}},{"generated":{"line":63,"column":36},"source":"src/lib/Images/index.js","original":{"line":47,"column":18}},{"generated":{"line":63,"column":37},"source":"src/lib/Images/index.js","original":{"line":47,"column":4}},{"name":"container","generated":{"line":64,"column":0},"source":"src/lib/Images/index.js","original":{"line":48,"column":4}},{"name":"insertAdjacentElement","generated":{"line":64,"column":14},"source":"src/lib/Images/index.js","original":{"line":48,"column":14}},{"generated":{"line":64,"column":35},"source":"src/lib/Images/index.js","original":{"line":48,"column":4}},{"generated":{"line":64,"column":36},"source":"src/lib/Images/index.js","original":{"line":48,"column":36}},{"generated":{"line":64,"column":47},"source":"src/lib/Images/index.js","original":{"line":48,"column":4}},{"name":"image","generated":{"line":64,"column":49},"source":"src/lib/Images/index.js","original":{"line":48,"column":49}},{"generated":{"line":64,"column":54},"source":"src/lib/Images/index.js","original":{"line":48,"column":4}},{"generated":{"line":65,"column":0},"source":"src/lib/Images/index.js","original":{"line":49,"column":3}},{"generated":{"line":66,"column":0},"source":"src/lib/Images/index.js","original":{"line":50,"column":2}},{"generated":{"line":68,"column":0},"source":"src/lib/Images/index.js","original":{"line":52,"column":2}},{"generated":{"line":68,"column":9},"source":"src/lib/Images/index.js","original":{"line":52,"column":9}},{"name":"next","generated":{"line":69,"column":0},"source":"src/lib/Images/index.js","original":{"line":53,"column":4}},{"generated":{"line":69,"column":14},"source":"src/lib/Images/index.js","original":{"line":52,"column":9}},{"name":"pre","generated":{"line":70,"column":0},"source":"src/lib/Images/index.js","original":{"line":54,"column":4}},{"generated":{"line":70,"column":12},"source":"src/lib/Images/index.js","original":{"line":52,"column":9}},{"name":"addSrc","generated":{"line":71,"column":0},"source":"src/lib/Images/index.js","original":{"line":55,"column":4}},{"generated":{"line":71,"column":12},"source":"src/lib/Images/index.js","original":{"line":55,"column":12}},{"name":"src","generated":{"line":71,"column":28},"source":"src/lib/Images/index.js","original":{"line":55,"column":13}},{"generated":{"line":71,"column":31},"source":"src/lib/Images/index.js","original":{"line":55,"column":12}},{"generated":{"line":71,"column":33},"source":"src/lib/Images/index.js","original":{"line":55,"column":21}},{"name":"srcList","generated":{"line":72,"column":0},"source":"src/lib/Images/index.js","original":{"line":56,"column":6}},{"name":"psuh","generated":{"line":72,"column":14},"source":"src/lib/Images/index.js","original":{"line":56,"column":14}},{"generated":{"line":72,"column":18},"source":"src/lib/Images/index.js","original":{"line":56,"column":6}},{"name":"src","generated":{"line":72,"column":19},"source":"src/lib/Images/index.js","original":{"line":56,"column":19}},{"generated":{"line":72,"column":22},"source":"src/lib/Images/index.js","original":{"line":56,"column":6}},{"name":"resetWidth","generated":{"line":73,"column":0},"source":"src/lib/Images/index.js","original":{"line":57,"column":6}},{"generated":{"line":74,"column":0},"source":"src/lib/Images/index.js","original":{"line":58,"column":5}},{"generated":{"line":74,"column":5},"source":"src/lib/Images/index.js","original":{"line":52,"column":9}},{"name":"removeSrc","generated":{"line":75,"column":0},"source":"src/lib/Images/index.js","original":{"line":59,"column":4}},{"generated":{"line":75,"column":15},"source":"src/lib/Images/index.js","original":{"line":59,"column":15}},{"name":"targetSrc","generated":{"line":75,"column":34},"source":"src/lib/Images/index.js","original":{"line":59,"column":16}},{"generated":{"line":75,"column":43},"source":"src/lib/Images/index.js","original":{"line":59,"column":15}},{"generated":{"line":75,"column":45},"source":"src/lib/Images/index.js","original":{"line":59,"column":30}},{"name":"srcList","generated":{"line":76,"column":0},"source":"src/lib/Images/index.js","original":{"line":60,"column":6}},{"name":"srcList","generated":{"line":76,"column":16},"source":"src/lib/Images/index.js","original":{"line":60,"column":16}},{"name":"filter","generated":{"line":76,"column":24},"source":"src/lib/Images/index.js","original":{"line":60,"column":24}},{"generated":{"line":76,"column":30},"source":"src/lib/Images/index.js","original":{"line":60,"column":16}},{"generated":{"line":76,"column":31},"source":"src/lib/Images/index.js","original":{"line":60,"column":31}},{"generated":{"line":77,"column":0},"source":"src/lib/Images/index.js","original":{"line":60,"column":31}},{"name":"src","generated":{"line":77,"column":15},"source":"src/lib/Images/index.js","original":{"line":60,"column":38}},{"name":"targetSrc","generated":{"line":77,"column":23},"source":"src/lib/Images/index.js","original":{"line":60,"column":46}},{"generated":{"line":77,"column":32},"source":"src/lib/Images/index.js","original":{"line":60,"column":31}},{"generated":{"line":78,"column":0},"source":"src/lib/Images/index.js","original":{"line":60,"column":31}},{"generated":{"line":78,"column":7},"source":"src/lib/Images/index.js","original":{"line":60,"column":16}},{"generated":{"line":78,"column":8},"source":"src/lib/Images/index.js","original":{"line":60,"column":6}},{"name":"resetWidth","generated":{"line":79,"column":0},"source":"src/lib/Images/index.js","original":{"line":61,"column":6}},{"generated":{"line":80,"column":0},"source":"src/lib/Images/index.js","original":{"line":62,"column":5}},{"generated":{"line":80,"column":5},"source":"src/lib/Images/index.js","original":{"line":52,"column":9}},{"name":"getContainer","generated":{"line":81,"column":0},"source":"src/lib/Images/index.js","original":{"line":63,"column":4}},{"generated":{"line":81,"column":18},"source":"src/lib/Images/index.js","original":{"line":63,"column":18}},{"generated":{"line":82,"column":0},"source":"src/lib/Images/index.js","original":{"line":63,"column":18}},{"name":"container","generated":{"line":82,"column":13},"source":"src/lib/Images/index.js","original":{"line":63,"column":24}},{"generated":{"line":82,"column":22},"source":"src/lib/Images/index.js","original":{"line":63,"column":18}},{"generated":{"line":83,"column":0},"source":"src/lib/Images/index.js","original":{"line":63,"column":18}},{"generated":{"line":84,"column":0},"source":"src/lib/Images/index.js","original":{"line":52,"column":9}},{"generated":{"line":84,"column":3},"source":"src/lib/Images/index.js","original":{"line":52,"column":2}},{"generated":{"line":85,"column":0},"source":"src/lib/Images/index.js","original":{"line":65,"column":1}},{"generated":{"line":85,"column":1},"source":"src/lib/Images/index.js","original":{"line":4,"column":0}},{"generated":{"line":87,"column":18},"source":"src/lib/Images/index.js","original":{"line":67,"column":15}},{"name":"create","generated":{"line":88,"column":0},"source":"src/lib/Images/index.js","original":{"line":68,"column":2}},{"generated":{"line":89,"column":0},"source":"src/lib/Images/index.js","original":{"line":67,"column":15}}],"sources":{"src/lib/Images/index.js":"import './style.css'\nimport getFixedIndex from '../getFixedIndex'\n\nconst create = ({\n  width, height, num, srcList, startIndex = 0,\n}) => {\n  const resetWidth = () => {\n    container.style.width = width * num\n  }\n\n  const getImage = (index) => {\n    const fixedIndex = getFixedIndex(srcList, index)\n\n    const src = srcList[fixedIndex]\n    const image = new Image(width, height)\n    image.src = src\n\n    return image\n  }\n\n  const next = () => {\n    current += 1\n\n    const newImage = getImage(current + (num - 1))\n    container.insertAdjacentElement('beforeend', newImage)\n\n    const firstImage = container.querySelector('img:first-child')\n    firstImage.remove()\n  }\n\n  const pre = () => {\n    current -= 1\n\n    const newImage = getImage(current)\n    container.insertAdjacentElement('afterbegin', newImage)\n\n    const lastImage = container.querySelector('img:last-child')\n    lastImage.remove()\n  }\n\n  const container = document.createElement('div')\n  container.className = 'images-container'\n  resetWidth()\n\n  let current = startIndex\n  for (let i = 0; i < num; i += 1) {\n    const image = getImage(current + i)\n    container.insertAdjacentElement('beforeend', image)\n  }\n  // current += num\n\n  return {\n    next,\n    pre,\n    addSrc: (src) => {\n      srcList.psuh(src)\n      resetWidth()\n    },\n    removeSrc: (targetSrc) => {\n      srcList = srcList.filter(src => src === targetSrc)\n      resetWidth()\n    },\n    getContainer: () => container,\n  }\n}\n\nexport default {\n  create,\n}\n"},"lineCount":null}},"hash":"7312d48376f9eb922ef846ff78573e67","cacheData":{"env":{}}}